{
    "release":26,
    "update":"2023-03-25",
    "version":"1.1.0harmattan26",
    "apk_url":"https://raw.githubusercontent.com/glKarin/com.n0n3m4.diii4a/package/idTech4A++_harmattan.1.1.0.26.apk",
    "changes":"  * Using SurfaceView for rendering, remove GLSurfaceView(Testing).\n  * Using DOOM3's Fx/Particle system implement Quake4's BSE incompletely for effects in Quake 4. The effects are bad now. Using set `bse_enabled` to 0 for disable effects.\n  * Remove my cvar `harm_g_alwaysRun`, so set original `in_alwaysRun` to 1 for run in Quake 4.\n  * Add simple beam model render in Prey(2006).\n  * Optimize skybox render in Prey(2006) by lvonasek."
}
